[
  {
    "title": "IEEE Standard for Wireless Access in Vehicular Environments--Security Services for Application and Management Messages",
    "code": "IEEE 1609.2",
    "organization": "IEEE",
    "url": "https://standards.ieee.org/ieee/1609.2/10258/",
    "isExternal": true
  },
  {
    "title": "Connected Intersections Implementation Guide",
    "code": "CTI 4501",
    "category": "Field",
    "organization": "",
    "url": "",
    "isExternal": true
  },
  {
    "title": "IEEE Standard for Wireless Access in Vehicular Environments (WAVE) - Certificate Management Interfaces for End Entities",
    "code": "IEEE 1609.2.1",
    "category": "Support",
    "organization": "IEEE",
    "url": "https://standards.ieee.org/ieee/1609.2.1/10728/",
    "isExternal": true
  },
  {
    "title": "IEEE Standard for Wireless Access in Vehicular Environments (WAVE)--Networking Services",
    "code": "IEEE 1609.3",
    "organization": "IEEE",
    "url": "https://standards.ieee.org/ieee/1609.3/10360/",
    "isExternal": true
  },
  {
    "title": "The JavaScript Object Notation (JSON) Data Interchange Format",
    "code": "IETF RFC 7159",
    "organization": "IETF",
    "url": "https://datatracker.ietf.org/doc/html/rfc7159",
    "isExternal": true
  },
  {
    "title": "The Transport Layer Security (TLS) Protocol Version 1.3",
    "code": "IETF RFC 8446",
    "organization": "IETF",
    "url": "https://datatracker.ietf.org/doc/html/rfc8446",
    "isExternal": true
  },
  {
    "title": "Intelligent transport systems — Cooperative ITS — Using V2I and I2V communications for applications related to signalized intersections",
    "code": "ISO 19091",
    "organization": "ISO",
    "url": "https://www.iso.org/standard/73781.html",
    "isExternal": true
  },
  {
    "title": "Intelligent transport systems — ITS station security services for secure session establishment and authentication between trusted devices",
    "code": "ISO 21177",
    "organization": "ISO",
    "url": "https://www.iso.org/standard/87225.html",
    "isExternal": true
  },
  {
    "title": "Taxonomy and definitions for terms related to driving automation systems for on-road motor vehicles",
    "code": "ISO/SAE PAS 22736",
    "category": "Vehicle",
    "organization": "ISO/SAE",
    "url": "https://www.iso.org/standard/73766.html",
    "isExternal": true
  },
  {
    "title": "Serial Data Networking",
    "code": "NMEA 0183",
    "organization": "",
    "url": "https://www.nmea.org/nmea-0183.html",
    "isExternal": true
  },
  {
    "title": "Object Definitions for Roadside Units (RSUs)",
    "code": "NTCIP 1218",
    "organization": "",
    "url": "https://www.ntcip.org/roadside-unit-rsu/",
    "isExternal": true
  },
  {
    "title": "V2X Communications Message Set Dictionary",
    "code": "SAE J2735",
    "organization": "",
    "url": "https://www.sae.org/standards/content/j2735_202409/",
    "isExternal": true
  },
  {
    "title": "On-Board System Requirements for V2V Safety Communications",
    "code": "SAE J2945/1",
    "organization": "",
    "url": "https://www.sae.org/standards/content/j2945/1_202004/",
    "isExternal": true
  },
  {
    "title": "Dedicated Short Range Communications (DSRC) Performance Requirements for V2V Safety Awareness",
    "code": "SAE J2945/2",
    "organization": "",
    "url": "https://www.sae.org/standards/content/j2945/2_201810/",
    "isExternal": true
  },
  {
    "title": "Requirements for Road Weather Applications",
    "code": "SAE J2945/3",
    "organization": "",
    "url": "https://www.sae.org/standards/content/j2945/3_202201/",
    "isExternal": true
  },
  {
    "title": "Road Safety Applications",
    "code": "SAE J2945/4",
    "organization": "",
    "url": "https://www.sae.org/standards/content/j2945/4_202305/",
    "isExternal": true
  },
  {
    "title": "Performance Requirements for Cooperative Adaptive Cruise Control (CACC) and Platooning",
    "code": "SAE J2945/6",
    "organization": "",
    "url": "https://www.sae.org/standards/content/j2945/6_202310/",
    "isExternal": true
  },
  {
    "title": "Vulnerable Road User Safety Message Minimum Performance Requirements",
    "code": "SAE J2945/9",
    "organization": "",
    "url": "https://www.sae.org/standards/content/j2945/9_201703/",
    "isExternal": true
  },
  {
    "title": "Minimum Requirements for Road Geometry and Attributes Definition",
    "code": "SAE J2945/A",
    "organization": "",
    "url": "https://www.sae.org/standards/content/j2945/a_202410/",
    "isExternal": true
  },
  {
    "title": "Recommended Practices for Signalized Intersection Applications",
    "code": "SAE J2945/B",
    "organization": "",
    "url": "https://www.sae.org/standards/content/j2945/b/",
    "isExternal": true
  },
  {
    "title": "Taxonomy and Definitions for Terms Related to Driving Automation Systems for On-Road Motor Vehicles",
    "code": "SAE J3016",
    "category": "Vehicle",
    "organization": "",
    "url": "https://www.sae.org/standards/content/j3016_202104/",
    "isExternal": true
  },
  {
    "title": "Onboard System Requirements for LTE-V2X V2V Safety Communications",
    "code": "SAE J3161/1",
    "organization": "",
    "url": "https://www.sae.org/standards/content/j3161/1_202409/",
    "isExternal": true
  },
  {
    "title": "Application Protocol and Requirements for Maneuver Sharing and Coordinating Service",
    "code": "SAE J3186",
    "organization": "",
    "url": "https://www.sae.org/standards/content/j3186_202303/",
    "isExternal": true
  },
  {
    "title": "Taxonomy and Definitions for Terms Related to Cooperative Driving Automation for On-Road Motor Vehicles",
    "code": "SAE J3216",
    "category": "Vehicle",
    "organization": "",
    "url": "https://www.sae.org/standards/content/j3216_202107/",
    "isExternal": true
  },
  {
    "title": "V2X Sensor-Sharing for Cooperative and Automated Driving",
    "code": "SAE J3224",
    "organization": "",
    "url": "https://www.sae.org/standards/content/j3224_202208/",
    "isExternal": true
  },
  {
    "title": "Listing of Provider Service Identifiers and Associated Application Technical Reports",
    "code": "SAE J3268",
    "organization": "",
    "url": "https://www.sae.org/standards/content/j3268_202303/",
    "isExternal": true
  },
  {
    "title": "Identity Management Entity within Security Services",
    "code": "SAE J3286",
    "category": "Vehicle",
    "organization": "",
    "url": "https://www.sae.org/standards/content/j3286/",
    "isExternal": true
  },
  {
    "title": "V2X Misbehavior Reporting",
    "code": "SAE J3287",
    "organization": "",
    "url": "https://www.sae.org/standards/content/j3287_202408/",
    "isExternal": true
  }
]